ml_base/__init__.py
ml_base/decorator.py
ml_base/ml_model.py
ml_base/version.txt
ml_base/utilities/__init__.py
ml_base/utilities/model_manager.py
ml_base-0.2.2.dist-info/LICENSE
ml_base-0.2.2.dist-info/METADATA
ml_base-0.2.2.dist-info/WHEEL
ml_base-0.2.2.dist-info/top_level.txt
ml_base-0.2.2.dist-info/RECORD
