Metadata-Version: 2.1
Name: ml-base
Version: 0.2.2
Summary: Base classes and utilities that are useful for deploying ML models.
Home-page: https://github.com/schmidtbri/ml-base
Author: Brian Schmidt
Author-email: 6666331+schmidtbri@users.noreply.github.com
Project-URL: Documentation, https://schmidtbri.github.io/ml-base/
Project-URL: Code, https://github.com/schmidtbri/ml-base
Project-URL: Tracker, https://github.com/schmidtbri/ml-base/issues
Keywords: machine learning,REST,service,model deployment
Classifier: Programming Language :: Python :: 3.8
Classifier: Programming Language :: Python :: 3.9
Classifier: Programming Language :: Python :: 3.10
Classifier: Programming Language :: Python :: 3.11
Classifier: Intended Audience :: Developers
Classifier: License :: OSI Approved :: BSD License
Classifier: Operating System :: OS Independent
Requires-Python: >=3.5
License-File: LICENSE
Requires-Dist: pydantic (>=1.5)
